windows11toast/__init__.py
windows11toast/constants.py
windows11toast/enums.py
windows11toast/media.py
windows11toast/notification.py
windows11toast/progress.py
windows11toast/py.typed
windows11toast/utils.py
windows11toast/xml_builder.py
windows11toast-1.2.6.dist-info/WHEEL
windows11toast-1.2.6.dist-info/METADATA
windows11toast-1.2.6.dist-info/RECORD
