Metadata-Version: 2.3
Name: windows11toast
Version: 1.2.6
Summary: 基于 WinRT 的 Windows 11 通知库
Author: zxb
Author-email: zxb <khassar@foxmail.com>
License: MIT
Classifier: Programming Language :: Python :: 3
Classifier: Programming Language :: Python :: 3.9
Classifier: Programming Language :: Python :: 3.10
Classifier: Programming Language :: Python :: 3.11
Classifier: Programming Language :: Python :: 3.12
Classifier: Programming Language :: Python :: 3.13
Classifier: License :: OSI Approved :: MIT License
Classifier: Topic :: Utilities
Classifier: Operating System :: Microsoft
Classifier: Operating System :: Microsoft :: Windows :: Windows 11
Requires-Dist: winrt-windows-data-xml-dom
Requires-Dist: winrt-windows-foundation
Requires-Dist: winrt-windows-foundation-collections
Requires-Dist: winrt-windows-globalization
Requires-Dist: winrt-windows-graphics-imaging
Requires-Dist: winrt-windows-media-core
Requires-Dist: winrt-windows-media-ocr
Requires-Dist: winrt-windows-media-playback
Requires-Dist: winrt-windows-media-speechsynthesis
Requires-Dist: winrt-windows-storage
Requires-Dist: winrt-windows-storage-streams
Requires-Dist: winrt-windows-ui-notifications
Requires-Python: >=3.9, <3.14
Project-URL: Bug Tracker, https://github.com/foreverseer-ex/windows11toast/issues
Project-URL: Homepage, https://github.com/foreverseer-ex/windows11toast
Project-URL: Repository, https://github.com/foreverseer-ex/windows11toast
